simplepinyin/__init__.py
simplepinyin/input_dict_nt_max.pickle
simplepinyin/lm.py
simplepinyin-0.1.1.dist-info/LICENSE
simplepinyin-0.1.1.dist-info/METADATA
simplepinyin-0.1.1.dist-info/WHEEL
simplepinyin-0.1.1.dist-info/top_level.txt
simplepinyin-0.1.1.dist-info/RECORD
